Workbook

Sheet FEB-2026
A1: Liquidación Eléctrica por Bodega – Metodología de Ingeniería
A3: INPUTS GENERALES | F3: BOLETA CGE (INPUTS DE FACTURACIÓN)
A4: Tarifa base día ($/kWh) | B4: 157 | C4: CLP/kWh | F4: Concepto | G4: Monto $
A5: Hora inicio jornada (Input) | B5: 08:00 | C5: hh:mm | F5: Electricidad Consumida $ | G5: 337537
A6: Hora inicio horario especial | B6: 18:00 | C6: hh:mm | F6: Potencia Punta $ | G6: 261203
A7: Factor horario especial (>18:00) | B7: 1 | C7: – | F7: Multa Reactiva $ | G7: 95798
A8: IVA | B8: 0.19 | C8: % | F8: Cargos Fijos $ | G8: 44477
F9: Intereses/Mora $ | G9: 35294
A11: INPUTS POR BODEGA (REMARCADOR + HORARIO EFECTIVO)
A12: Bodega | B12: Giro | C12: kWh Remarcador | D12: Hora salida (Input) | E12: Carga inductiva (SI/NO) | F12: Pago con atraso (SI/NO) | G12: % post-18 (calc) | H12: kWh post-18 (calc) | I12: kWh día (calc)
A13: E-1 | B13: Mantención autos | C13: 857 | D13: 0.79166667 | E13: NO | F13: NO | G13: =IF(D13="",0,MAX(0,D13-$B6)/MAX(0.000001,(D13-$B5))) -> 0.090909091 | H13: =C13*G13 -> 77.909091 | I13: =C13-H13 -> 779.09091
A14: E-2 | B14: Equipamiento eléctrico | C14: 283 | D14: 0.77083333 | E14: NO | F14: NO | G14: =IF(D14="",0,MAX(0,D14-$B6)/MAX(0.000001,(D14-$B5))) -> 0.047619048 | H14: =C14*G14 -> 13.47619 | I14: =C14-H14 -> 269.52381
A15: E-3 | B15: Matricería | C15: 870 | D15: 0.77083333 | E15: SI | F15: NO | G15: =IF(D15="",0,MAX(0,D15-$B6)/MAX(0.000001,(D15-$B5))) -> 0.047619048 | H15: =C15*G15 -> 41.428571 | I15: =C15-H15 -> 828.57143
A16: E-4 | B16: Matricería | C16: 300 | D16: 0.77083333 | E16: SI | F16: NO | G16: =IF(D16="",0,MAX(0,D16-$B6)/MAX(0.000001,(D16-$B5))) -> 0.047619048 | H16: =C16*G16 -> 14.285714 | I16: =C16-H16 -> 285.71429
A17: E-5 | B17: Torno CNC | C17: 508 | D17: 0.77083333 | E17: SI | F17: NO | G17: =IF(D17="",0,MAX(0,D17-$B6)/MAX(0.000001,(D17-$B5))) -> 0.047619048 | H17: =C17*G17 -> 24.190476 | I17: =C17-H17 -> 483.80952
A18: E-6 | B18: Torno/Fresadora | C18: 900 | D18: 0.79166667 | E18: SI | F18: SI | G18: =IF(D18="",0,MAX(0,D18-$B6)/MAX(0.000001,(D18-$B5))) -> 0.090909091 | H18: =C18*G18 -> 81.818182 | I18: =C18-H18 -> 818.18182
A19: E-7 | B19: Soldadura | C19: 365 | D19: 0.77083333 | E19: SI | F19: NO | G19: =IF(D19="",0,MAX(0,D19-$B6)/MAX(0.000001,(D19-$B5))) -> 0.047619048 | H19: =C19*G19 -> 17.380952 | I19: =C19-H19 -> 347.61905
A20: TOTAL | C20: =SUM(C13:C19) -> 4083 | H20: =SUM(H13:H19) -> 270.48918 | I20: =SUM(I13:I19) -> 3812.5108
A22: LIQUIDACIÓN POR BODEGA (ASIGNACIÓN DE COSTOS DE BOLETA + CRITERIO HORARIO)
A23: Bodega | B23: kWh | C23: % Energía | D23: $ Energía | E23: kWh post-18 | F23: % Punta (calc) | G23: $ Punta | H23: % Reactiva | I23: $ Reactiva | J23: $ Cargos Fijos | K23: % Interés | L23: $ Interés | M23: TOTAL NETO $ | N23: IVA | O23: TOTAL c/IVA $
A24: =A13 -> E-1 | B24: =C13 -> 857 | C24: =IFERROR(B24/SUM(B24:B30),0) -> 0.20989469 | D24: =C24*$G5 -> 70847.222 | E24: =H13 -> 77.909091 | F24: =IFERROR(E24/SUM(E24:E30),0) -> 0.28803034 | G24: =F24*$G6 -> 75234.39 | H24: =IF($E13="SI",1,0)/MAX(1,COUNTIF($E13:$E19,"SI")) -> 0 | I24: =H24*$G7 -> 0 | J24: =($G8*0.5/7)+($G8*0.5*C24) -> 7844.6715 | K24: =IF($F13="SI",1,0)/MAX(1,COUNTIF($F13:$F19,"SI")) -> 0 | L24: =K24*$G$9 -> 0 | M24: =D24+G24+I24+J24+L24 -> 153926.28 | N24: =M24*$B8 -> 29245.994 | O24: =M24+N24 -> 183172.28
A25: =A14 -> E-2 | B25: =C14 -> 283 | C25: =IFERROR(B25/SUM(B24:B30),0) -> 0.069311781 | D25: =C25*$G5 -> 23395.29 | E25: =H14 -> 13.47619 | F25: =IFERROR(E25/SUM(E24:E30),0) -> 0.049821551 | G25: =F25*$G6 -> 13013.539 | H25: =IF($E14="SI",1,0)/MAX(1,COUNTIF($E13:$E19,"SI")) -> 0 | I25: =H25*$G7 -> 0 | J25: =($G8*0.5/7)+($G8*0.5*C25) -> 4718.3186 | K25: =IF($F14="SI",1,0)/MAX(1,COUNTIF($F13:$F19,"SI")) -> 0 | L25: =K25*$G$9 -> 0 | M25: =D25+G25+I25+J25+L25 -> 41127.148 | N25: =M25*$B8 -> 7814.1581 | O25: =M25+N25 -> 48941.306
A26: =A15 -> E-3 | B26: =C15 -> 870 | C26: =IFERROR(B26/SUM(B24:B30),0) -> 0.21307862 | D26: =C26*$G5 -> 71921.918 | E26: =H15 -> 41.428571 | F26: =IFERROR(E26/SUM(E24:E30),0) -> 0.15316166 | G26: =F26*$G6 -> 40006.285 | H26: =IF($E15="SI",1,0)/MAX(1,COUNTIF($E13:$E19,"SI")) -> 0.2 | I26: =H26*$G7 -> 19159.6 | J26: =($G8*0.5/7)+($G8*0.5*C26) -> 7915.4774 | K26: =IF($F15="SI",1,0)/MAX(1,COUNTIF($F13:$F19,"SI")) -> 0 | L26: =K26*$G$9 -> 0 | M26: =D26+G26+I26+J26+L26 -> 139003.28 | N26: =M26*$B8 -> 26410.623 | O26: =M26+N26 -> 165413.9
A27: =A16 -> E-4 | B27: =C16 -> 300 | C27: =IFERROR(B27/SUM(B24:B30),0) -> 0.073475386 | D27: =C27*$G5 -> 24800.661 | E27: =H16 -> 14.285714 | F27: =IFERROR(E27/SUM(E24:E30),0) -> 0.052814366 | G27: =F27*$G6 -> 13795.271 | H27: =IF($E16="SI",1,0)/MAX(1,COUNTIF($E13:$E19,"SI")) -> 0.2 | I27: =H27*$G7 -> 19159.6 | J27: =($G8*0.5/7)+($G8*0.5*C27) -> 4810.9109 | K27: =IF($F16="SI",1,0)/MAX(1,COUNTIF($F13:$F19,"SI")) -> 0 | L27: =K27*$G$9 -> 0 | M27: =D27+G27+I27+J27+L27 -> 62566.443 | N27: =M27*$B8 -> 11887.624 | O27: =M27+N27 -> 74454.067
A28: =A17 -> E-5 | B28: =C17 -> 508 | C28: =IFERROR(B28/SUM(B24:B30),0) -> 0.12441832 | D28: =C28*$G5 -> 41995.786 | E28: =H17 -> 24.190476 | F28: =IFERROR(E28/SUM(E24:E30),0) -> 0.089432326 | G28: =F28*$G6 -> 23359.992 | H28: =IF($E17="SI",1,0)/MAX(1,COUNTIF($E13:$E19,"SI")) -> 0.2 | I28: =H28*$G7 -> 19159.6 | J28: =($G8*0.5/7)+($G8*0.5*C28) -> 5943.8054 | K28: =IF($F17="SI",1,0)/MAX(1,COUNTIF($F13:$F19,"SI")) -> 0 | L28: =K28*$G$9 -> 0 | M28: =D28+G28+I28+J28+L28 -> 90459.184 | N28: =M28*$B8 -> 17187.245 | O28: =M28+N28 -> 107646.43
A29: =A18 -> E-6 | B29: =C18 -> 900 | C29: =IFERROR(B29/SUM(B24:B30),0) -> 0.22042616 | D29: =C29*$G5 -> 74401.984 | E29: =H18 -> 81.818182 | F29: =IFERROR(E29/SUM(E24:E30),0) -> 0.30248228 | G29: =F29*$G6 -> 79009.278 | H29: =IF($E18="SI",1,0)/MAX(1,COUNTIF($E13:$E19,"SI")) -> 0.2 | I29: =H29*$G7 -> 19159.6 | J29: =($G8*0.5/7)+($G8*0.5*C29) -> 8078.8757 | K29: =IF($F18="SI",1,0)/MAX(1,COUNTIF($F13:$F19,"SI")) -> 1 | L29: =K29*$G$9 -> 35294 | M29: =D29+G29+I29+J29+L29 -> 215943.74 | N29: =M29*$B8 -> 41029.31 | O29: =M29+N29 -> 256973.05
A30: =A19 -> E-7 | B30: =C19 -> 365 | C30: =IFERROR(B30/SUM(B24:B30),0) -> 0.089395053 | D30: =C30*$G5 -> 30174.138 | E30: =H19 -> 17.380952 | F30: =IFERROR(E30/SUM(E24:E30),0) -> 0.064257478 | G30: =F30*$G6 -> 16784.246 | H30: =IF($E19="SI",1,0)/MAX(1,COUNTIF($E13:$E19,"SI")) -> 0.2 | I30: =H30*$G7 -> 19159.6 | J30: =($G8*0.5/7)+($G8*0.5*C30) -> 5164.9404 | K30: =IF($F19="SI",1,0)/MAX(1,COUNTIF($F13:$F19,"SI")) -> 0 | L30: =K30*$G$9 -> 0 | M30: =D30+G30+I30+J30+L30 -> 71282.924 | N30: =M30*$B8 -> 13543.756 | O30: =M30+N30 -> 84826.68
A31: TOTAL | B31: =SUM(B24:B30) -> 4083 | D31: =SUM(D24:D30) -> 337537 | G31: =SUM(G24:G30) -> 261203 | I31: =SUM(I24:I30) -> 95798 | J31: =SUM(J24:J30) -> 44477 | L31: =SUM(L24:L30) -> 35294 | M31: =SUM(M24:M30) -> 774309 | N31: =SUM(N24:N30) -> 147118.71 | O31: =SUM(O24:O30) -> 921427.71
A33: Nota metodológica: % Punta se calcula proporcionalmente al kWh post-18 (según Hora salida por bodega). Reactiva se asigna a bodegas con carga inductiva. Intereses/Mora se asigna solo a responsables marcados con atraso.

Sheet MAR-2026
A1: Liquidación Eléctrica por Bodega – Metodología de Ingeniería
A3: INPUTS GENERALES | F3: BOLETA CGE (INPUTS DE FACTURACIÓN)
A4: Tarifa base día ($/kWh) | B4: 157 | C4: CLP/kWh | F4: Concepto | G4: Monto $
A5: Hora inicio jornada (Input) | B5: 08:00 | C5: hh:mm | F5: Electricidad Consumida $ | G5: 560000
A6: Hora inicio horario especial | B6: 18:00 | C6: hh:mm | F6: Potencia Punta $ | G6: 321770
A7: Factor horario especial (>18:00) | B7: 1 | C7: – | F7: Multa Reactiva $ | G7: 95798
A8: IVA | B8: 0.19 | C8: % | F8: Cargos Fijos $ | G8: 44477
F9: Intereses/Mora $ | G9: 35294
A11: INPUTS POR BODEGA (REMARCADOR + HORARIO EFECTIVO)
A12: Bodega | B12: Giro | C12: kWh Remarcador | D12: Hora salida (Input) | E12: Carga inductiva (SI/NO) | F12: Pago con atraso (SI/NO) | G12: % post-18 (calc) | H12: kWh post-18 (calc) | I12: kWh día (calc)
A13: E-1 | B13: Mantención autos | C13: 857 | D13: 0.79166667 | E13: NO | F13: NO | G13: =IF(D13="",0,MAX(0,D13-$B6)/MAX(0.000001,(D13-$B5))) -> 0.090909091 | H13: =C13*G13 -> 77.909091 | I13: =C13-H13 -> 779.09091
A14: E-2 | B14: Equipamiento eléctrico | C14: 283 | D14: 0.77083333 | E14: NO | F14: NO | G14: =IF(D14="",0,MAX(0,D14-$B6)/MAX(0.000001,(D14-$B5))) -> 0.047619048 | H14: =C14*G14 -> 13.47619 | I14: =C14-H14 -> 269.52381
A15: E-3 | B15: Matricería | C15: 870 | D15: 0.77083333 | E15: SI | F15: NO | G15: =IF(D15="",0,MAX(0,D15-$B6)/MAX(0.000001,(D15-$B5))) -> 0.047619048 | H15: =C15*G15 -> 41.428571 | I15: =C15-H15 -> 828.57143
A16: E-4 | B16: Matricería | C16: 300 | D16: 0.77083333 | E16: SI | F16: NO | G16: =IF(D16="",0,MAX(0,D16-$B6)/MAX(0.000001,(D16-$B5))) -> 0.047619048 | H16: =C16*G16 -> 14.285714 | I16: =C16-H16 -> 285.71429
A17: E-5 | B17: Torno CNC | C17: 508 | D17: 0.77083333 | E17: SI | F17: NO | G17: =IF(D17="",0,MAX(0,D17-$B6)/MAX(0.000001,(D17-$B5))) -> 0.047619048 | H17: =C17*G17 -> 24.190476 | I17: =C17-H17 -> 483.80952
A18: E-6 | B18: Torno/Fresadora | C18: 900 | D18: 0.79166667 | E18: SI | F18: SI | G18: =IF(D18="",0,MAX(0,D18-$B6)/MAX(0.000001,(D18-$B5))) -> 0.090909091 | H18: =C18*G18 -> 81.818182 | I18: =C18-H18 -> 818.18182
A19: E-7 | B19: Soldadura | C19: 365 | D19: 0.77083333 | E19: SI | F19: NO | G19: =IF(D19="",0,MAX(0,D19-$B6)/MAX(0.000001,(D19-$B5))) -> 0.047619048 | H19: =C19*G19 -> 17.380952 | I19: =C19-H19 -> 347.61905
A20: TOTAL | C20: =SUM(C13:C19) -> 4083 | H20: =SUM(H13:H19) -> 270.48918 | I20: =SUM(I13:I19) -> 3812.5108
A22: LIQUIDACIÓN POR BODEGA (ASIGNACIÓN DE COSTOS DE BOLETA + CRITERIO HORARIO)
A23: Bodega | B23: kWh | C23: % Energía | D23: $ Energía | E23: kWh post-18 | F23: % Punta (calc) | G23: $ Punta | H23: % Reactiva | I23: $ Reactiva | J23: $ Cargos Fijos | K23: % Interés | L23: $ Interés | M23: TOTAL NETO $ | N23: IVA | O23: TOTAL c/IVA $
A24: =A13 -> E-1 | B24: =C13 -> 857 | C24: =IFERROR(B24/SUM(B24:B30),0) -> 0.20989469 | D24: =C24*$G5 -> 117541.02 | E24: =H13 -> 77.909091 | F24: =IFERROR(E24/SUM(E24:E30),0) -> 0.28803034 | G24: =F24*$G6 -> 92679.524 | H24: =IF($E13="SI",1,0)/MAX(1,COUNTIF($E13:$E19,"SI")) -> 0 | I24: =H24*$G7 -> 0 | J24: =($G8*0.5/7)+($G8*0.5*C24) -> 7844.6715 | K24: =IF($F13="SI",1,0)/MAX(1,COUNTIF($F13:$F19,"SI")) -> 0 | L24: =K24*$G$9 -> 0 | M24: =D24+G24+I24+J24+L24 -> 218065.22 | N24: =M24*$B8 -> 41432.392 | O24: =M24+N24 -> 259497.61
A25: =A14 -> E-2 | B25: =C14 -> 283 | C25: =IFERROR(B25/SUM(B24:B30),0) -> 0.069311781 | D25: =C25*$G5 -> 38814.597 | E25: =H14 -> 13.47619 | F25: =IFERROR(E25/SUM(E24:E30),0) -> 0.049821551 | G25: =F25*$G6 -> 16031.081 | H25: =IF($E14="SI",1,0)/MAX(1,COUNTIF($E13:$E19,"SI")) -> 0 | I25: =H25*$G7 -> 0 | J25: =($G8*0.5/7)+($G8*0.5*C25) -> 4718.3186 | K25: =IF($F14="SI",1,0)/MAX(1,COUNTIF($F13:$F19,"SI")) -> 0 | L25: =K25*$G$9 -> 0 | M25: =D25+G25+I25+J25+L25 -> 59563.996 | N25: =M25*$B8 -> 11317.159 | O25: =M25+N25 -> 70881.156
A26: =A15 -> E-3 | B26: =C15 -> 870 | C26: =IFERROR(B26/SUM(B24:B30),0) -> 0.21307862 | D26: =C26*$G5 -> 119324.03 | E26: =H15 -> 41.428571 | F26: =IFERROR(E26/SUM(E24:E30),0) -> 0.15316166 | G26: =F26*$G6 -> 49282.827 | H26: =IF($E15="SI",1,0)/MAX(1,COUNTIF($E13:$E19,"SI")) -> 0.2 | I26: =H26*$G7 -> 19159.6 | J26: =($G8*0.5/7)+($G8*0.5*C26) -> 7915.4774 | K26: =IF($F15="SI",1,0)/MAX(1,COUNTIF($F13:$F19,"SI")) -> 0 | L26: =K26*$G$9 -> 0 | M26: =D26+G26+I26+J26+L26 -> 195681.93 | N26: =M26*$B8 -> 37179.567 | O26: =M26+N26 -> 232861.5
A27: =A16 -> E-4 | B27: =C16 -> 300 | C27: =IFERROR(B27/SUM(B24:B30),0) -> 0.073475386 | D27: =C27*$G5 -> 41146.216 | E27: =H16 -> 14.285714 | F27: =IFERROR(E27/SUM(E24:E30),0) -> 0.052814366 | G27: =F27*$G6 -> 16994.078 | H27: =IF($E16="SI",1,0)/MAX(1,COUNTIF($E13:$E19,"SI")) -> 0.2 | I27: =H27*$G7 -> 19159.6 | J27: =($G8*0.5/7)+($G8*0.5*C27) -> 4810.9109 | K27: =IF($F16="SI",1,0)/MAX(1,COUNTIF($F13:$F19,"SI")) -> 0 | L27: =K27*$G$9 -> 0 | M27: =D27+G27+I27+J27+L27 -> 82110.805 | N27: =M27*$B8 -> 15601.053 | O27: =M27+N27 -> 97711.858
A28: =A17 -> E-5 | B28: =C17 -> 508 | C28: =IFERROR(B28/SUM(B24:B30),0) -> 0.12441832 | D28: =C28*$G5 -> 69674.259 | E28: =H17 -> 24.190476 | F28: =IFERROR(E28/SUM(E24:E30),0) -> 0.089432326 | G28: =F28*$G6 -> 28776.639 | H28: =IF($E17="SI",1,0)/MAX(1,COUNTIF($E13:$E19,"SI")) -> 0.2 | I28: =H28*$G7 -> 19159.6 | J28: =($G8*0.5/7)+($G8*0.5*C28) -> 5943.8054 | K28: =IF($F17="SI",1,0)/MAX(1,COUNTIF($F13:$F19,"SI")) -> 0 | L28: =K28*$G$9 -> 0 | M28: =D28+G28+I28+J28+L28 -> 123554.3 | N28: =M28*$B8 -> 23475.318 | O28: =M28+N28 -> 147029.62
A29: =A18 -> E-6 | B29: =C18 -> 900 | C29: =IFERROR(B29/SUM(B24:B30),0) -> 0.22042616 | D29: =C29*$G5 -> 123438.65 | E29: =H18 -> 81.818182 | F29: =IFERROR(E29/SUM(E24:E30),0) -> 0.30248228 | G29: =F29*$G6 -> 97329.722 | H29: =IF($E18="SI",1,0)/MAX(1,COUNTIF($E13:$E19,"SI")) -> 0.2 | I29: =H29*$G7 -> 19159.6 | J29: =($G8*0.5/7)+($G8*0.5*C29) -> 8078.8757 | K29: =IF($F18="SI",1,0)/MAX(1,COUNTIF($F13:$F19,"SI")) -> 1 | L29: =K29*$G$9 -> 35294 | M29: =D29+G29+I29+J29+L29 -> 283300.85 | N29: =M29*$B8 -> 53827.161 | O29: =M29+N29 -> 337128.01
A30: =A19 -> E-7 | B30: =C19 -> 365 | C30: =IFERROR(B30/SUM(B24:B30),0) -> 0.089395053 | D30: =C30*$G5 -> 50061.229 | E30: =H19 -> 17.380952 | F30: =IFERROR(E30/SUM(E24:E30),0) -> 0.064257478 | G30: =F30*$G6 -> 20676.129 | H30: =IF($E19="SI",1,0)/MAX(1,COUNTIF($E13:$E19,"SI")) -> 0.2 | I30: =H30*$G7 -> 19159.6 | J30: =($G8*0.5/7)+($G8*0.5*C30) -> 5164.9404 | K30: =IF($F19="SI",1,0)/MAX(1,COUNTIF($F13:$F19,"SI")) -> 0 | L30: =K30*$G$9 -> 0 | M30: =D30+G30+I30+J30+L30 -> 95061.899 | N30: =M30*$B8 -> 18061.761 | O30: =M30+N30 -> 113123.66
A31: TOTAL | B31: =SUM(B24:B30) -> 4083 | D31: =SUM(D24:D30) -> 560000 | G31: =SUM(G24:G30) -> 321770 | I31: =SUM(I24:I30) -> 95798 | J31: =SUM(J24:J30) -> 44477 | L31: =SUM(L24:L30) -> 35294 | M31: =SUM(M24:M30) -> 1057339 | N31: =SUM(N24:N30) -> 200894.41 | O31: =SUM(O24:O30) -> 1258233.4
A33: Nota metodológica: % Punta se calcula proporcionalmente al kWh post-18 (según Hora salida por bodega). Reactiva se asigna a bodegas con carga inductiva. Intereses/Mora se asigna solo a responsables marcados con atraso.

Sheet ABR-20226
A1: Liquidación Eléctrica por Bodega – Metodología de Ingeniería
A3: INPUTS GENERALES | F3: BOLETA CGE (INPUTS DE FACTURACIÓN)
A4: Tarifa base día ($/kWh) | B4: 157 | C4: CLP/kWh | F4: Concepto | G4: Monto $
A5: Hora inicio jornada (Input) | B5: 08:00 | C5: hh:mm | F5: Electricidad Consumida $ | G5: 456000
A6: Hora inicio horario especial | B6: 18:00 | C6: hh:mm | F6: Potencia Punta $ | G6: 456000
A7: Factor horario especial (>18:00) | B7: 1 | C7: – | F7: Multa Reactiva $ | G7: 56987
A8: IVA | B8: 0.19 | C8: % | F8: Cargos Fijos $ | G8: 56789
F9: Intereses/Mora $ | G9: 45678
A11: INPUTS POR BODEGA (REMARCADOR + HORARIO EFECTIVO)
A12: Bodega | B12: Giro | C12: kWh Remarcador | D12: Hora salida (Input) | E12: Carga inductiva (SI/NO) | F12: Pago con atraso (SI/NO) | G12: % post-18 (calc) | H12: kWh post-18 (calc) | I12: kWh día (calc)
A13: E-1 | B13: Mantención autos | C13: 987 | D13: 0.79166667 | E13: NO | F13: NO | G13: =IF(D13="",0,MAX(0,D13-$B6)/MAX(0.000001,(D13-$B5))) -> 0.090909091 | H13: =C13*G13 -> 89.727273 | I13: =C13-H13 -> 897.27273
A14: E-2 | B14: Equipamiento eléctrico | C14: 569 | D14: 0.77083333 | E14: NO | F14: NO | G14: =IF(D14="",0,MAX(0,D14-$B6)/MAX(0.000001,(D14-$B5))) -> 0.047619048 | H14: =C14*G14 -> 27.095238 | I14: =C14-H14 -> 541.90476
A15: E-3 | B15: Matricería | C15: 400 | D15: 0.77083333 | E15: SI | F15: NO | G15: =IF(D15="",0,MAX(0,D15-$B6)/MAX(0.000001,(D15-$B5))) -> 0.047619048 | H15: =C15*G15 -> 19.047619 | I15: =C15-H15 -> 380.95238
A16: E-4 | B16: Matricería | C16: 506 | D16: 0.77083333 | E16: SI | F16: NO | G16: =IF(D16="",0,MAX(0,D16-$B6)/MAX(0.000001,(D16-$B5))) -> 0.047619048 | H16: =C16*G16 -> 24.095238 | I16: =C16-H16 -> 481.90476
A17: E-5 | B17: Torno CNC | C17: 497 | D17: 0.77083333 | E17: SI | F17: NO | G17: =IF(D17="",0,MAX(0,D17-$B6)/MAX(0.000001,(D17-$B5))) -> 0.047619048 | H17: =C17*G17 -> 23.666667 | I17: =C17-H17 -> 473.33333
A18: E-6 | B18: Torno/Fresadora | C18: 900 | D18: 0.79166667 | E18: SI | F18: SI | G18: =IF(D18="",0,MAX(0,D18-$B6)/MAX(0.000001,(D18-$B5))) -> 0.090909091 | H18: =C18*G18 -> 81.818182 | I18: =C18-H18 -> 818.18182
A19: E-7 | B19: Soldadura | C19: 365 | D19: 0.77083333 | E19: SI | F19: NO | G19: =IF(D19="",0,MAX(0,D19-$B6)/MAX(0.000001,(D19-$B5))) -> 0.047619048 | H19: =C19*G19 -> 17.380952 | I19: =C19-H19 -> 347.61905
A20: TOTAL | C20: =SUM(C13:C19) -> 4224 | H20: =SUM(H13:H19) -> 282.83117 | I20: =SUM(I13:I19) -> 3941.1688
A22: LIQUIDACIÓN POR BODEGA (ASIGNACIÓN DE COSTOS DE BOLETA + CRITERIO HORARIO)
A23: Bodega | B23: kWh | C23: % Energía | D23: $ Energía | E23: kWh post-18 | F23: % Punta (calc) | G23: $ Punta | H23: % Reactiva | I23: $ Reactiva | J23: $ Cargos Fijos | K23: % Interés | L23: $ Interés | M23: TOTAL NETO $ | N23: IVA | O23: TOTAL c/IVA $
A24: =A13 -> E-1 | B24: =C13 -> 987 | C24: =IFERROR(B24/SUM(B24:B30),0) -> 0.23366477 | D24: =C24*$G5 -> 106551.14 | E24: =H13 -> 89.727273 | F24: =IFERROR(E24/SUM(E24:E30),0) -> 0.31724676 | G24: =F24*$G6 -> 144664.52 | H24: =IF($E13="SI",1,0)/MAX(1,COUNTIF($E13:$E19,"SI")) -> 0 | I24: =H24*$G7 -> 0 | J24: =($G8*0.5/7)+($G8*0.5*C24) -> 10691.152 | K24: =IF($F13="SI",1,0)/MAX(1,COUNTIF($F13:$F19,"SI")) -> 0 | L24: =K24*$G$9 -> 0 | M24: =D24+G24+I24+J24+L24 -> 261906.81 | N24: =M24*$B8 -> 49762.294 | O24: =M24+N24 -> 311669.11
A25: =A14 -> E-2 | B25: =C14 -> 569 | C25: =IFERROR(B25/SUM(B24:B30),0) -> 0.13470644 | D25: =C25*$G5 -> 61426.136 | E25: =H14 -> 27.095238 | F25: =IFERROR(E25/SUM(E24:E30),0) -> 0.095800043 | G25: =F25*$G6 -> 43684.82 | H25: =IF($E14="SI",1,0)/MAX(1,COUNTIF($E13:$E19,"SI")) -> 0 | I25: =H25*$G7 -> 0 | J25: =($G8*0.5/7)+($G8*0.5*C25) -> 7881.2791 | K25: =IF($F14="SI",1,0)/MAX(1,COUNTIF($F13:$F19,"SI")) -> 0 | L25: =K25*$G$9 -> 0 | M25: =D25+G25+I25+J25+L25 -> 112992.24 | N25: =M25*$B8 -> 21468.525 | O25: =M25+N25 -> 134460.76
A26: =A15 -> E-3 | B26: =C15 -> 400 | C26: =IFERROR(B26/SUM(B24:B30),0) -> 0.09469697 | D26: =C26*$G5 -> 43181.818 | E26: =H15 -> 19.047619 | F26: =IFERROR(E26/SUM(E24:E30),0) -> 0.067346252 | G26: =F26*$G6 -> 30709.891 | H26: =IF($E15="SI",1,0)/MAX(1,COUNTIF($E13:$E19,"SI")) -> 0.2 | I26: =H26*$G7 -> 11397.4 | J26: =($G8*0.5/7)+($G8*0.5*C26) -> 6745.2302 | K26: =IF($F15="SI",1,0)/MAX(1,COUNTIF($F13:$F19,"SI")) -> 0 | L26: =K26*$G$9 -> 0 | M26: =D26+G26+I26+J26+L26 -> 92034.339 | N26: =M26*$B8 -> 17486.524 | O26: =M26+N26 -> 109520.86
A27: =A16 -> E-4 | B27: =C16 -> 506 | C27: =IFERROR(B27/SUM(B24:B30),0) -> 0.11979167 | D27: =C27*$G5 -> 54625 | E27: =H16 -> 24.095238 | F27: =IFERROR(E27/SUM(E24:E30),0) -> 0.085193008 | G27: =F27*$G6 -> 38848.012 | H27: =IF($E16="SI",1,0)/MAX(1,COUNTIF($E13:$E19,"SI")) -> 0.2 | I27: =H27*$G7 -> 11397.4 | J27: =($G8*0.5/7)+($G8*0.5*C27) -> 7457.7816 | K27: =IF($F16="SI",1,0)/MAX(1,COUNTIF($F13:$F19,"SI")) -> 0 | L27: =K27*$G$9 -> 0 | M27: =D27+G27+I27+J27+L27 -> 112328.19 | N27: =M27*$B8 -> 21342.357 | O27: =M27+N27 -> 133670.55
A28: =A17 -> E-5 | B28: =C17 -> 497 | C28: =IFERROR(B28/SUM(B24:B30),0) -> 0.11766098 | D28: =C28*$G5 -> 53653.409 | E28: =H17 -> 23.666667 | F28: =IFERROR(E28/SUM(E24:E30),0) -> 0.083677718 | G28: =F28*$G6 -> 38157.039 | H28: =IF($E17="SI",1,0)/MAX(1,COUNTIF($E13:$E19,"SI")) -> 0.2 | I28: =H28*$G7 -> 11397.4 | J28: =($G8*0.5/7)+($G8*0.5*C28) -> 7397.282 | K28: =IF($F17="SI",1,0)/MAX(1,COUNTIF($F13:$F19,"SI")) -> 0 | L28: =K28*$G$9 -> 0 | M28: =D28+G28+I28+J28+L28 -> 110605.13 | N28: =M28*$B8 -> 21014.975 | O28: =M28+N28 -> 131620.11
A29: =A18 -> E-6 | B29: =C18 -> 900 | C29: =IFERROR(B29/SUM(B24:B30),0) -> 0.21306818 | D29: =C29*$G5 -> 97159.091 | E29: =H18 -> 81.818182 | F29: =IFERROR(E29/SUM(E24:E30),0) -> 0.28928276 | G29: =F29*$G6 -> 131912.94 | H29: =IF($E18="SI",1,0)/MAX(1,COUNTIF($E13:$E19,"SI")) -> 0.2 | I29: =H29*$G7 -> 11397.4 | J29: =($G8*0.5/7)+($G8*0.5*C29) -> 10106.322 | K29: =IF($F18="SI",1,0)/MAX(1,COUNTIF($F13:$F19,"SI")) -> 1 | L29: =K29*$G$9 -> 45678 | M29: =D29+G29+I29+J29+L29 -> 296253.75 | N29: =M29*$B8 -> 56288.213 | O29: =M29+N29 -> 352541.97
A30: =A19 -> E-7 | B30: =C19 -> 365 | C30: =IFERROR(B30/SUM(B24:B30),0) -> 0.086410985 | D30: =C30*$G5 -> 39403.409 | E30: =H19 -> 17.380952 | F30: =IFERROR(E30/SUM(E24:E30),0) -> 0.061453455 | G30: =F30*$G6 -> 28022.775 | H30: =IF($E19="SI",1,0)/MAX(1,COUNTIF($E13:$E19,"SI")) -> 0.2 | I30: =H30*$G7 -> 11397.4 | J30: =($G8*0.5/7)+($G8*0.5*C30) -> 6509.9539 | K30: =IF($F19="SI",1,0)/MAX(1,COUNTIF($F13:$F19,"SI")) -> 0 | L30: =K30*$G$9 -> 0 | M30: =D30+G30+I30+J30+L30 -> 85333.538 | N30: =M30*$B8 -> 16213.372 | O30: =M30+N30 -> 101546.91
A31: TOTAL | B31: =SUM(B24:B30) -> 4224 | D31: =SUM(D24:D30) -> 456000 | G31: =SUM(G24:G30) -> 456000 | I31: =SUM(I24:I30) -> 56987 | J31: =SUM(J24:J30) -> 56789 | L31: =SUM(L24:L30) -> 45678 | M31: =SUM(M24:M30) -> 1071454 | N31: =SUM(N24:N30) -> 203576.26 | O31: =SUM(O24:O30) -> 1275030.3
A33: Nota metodológica: % Punta se calcula proporcionalmente al kWh post-18 (según Hora salida por bodega). Reactiva se asigna a bodegas con carga inductiva. Intereses/Mora se asigna solo a responsables marcados con atraso.

Sheet Inputs_Mes
A1: Liquidación Eléctrica por Bodega – Metodología de Ingeniería | B1: Giro | C1: kWh Remarcador | D1: Usa después 18:00 (SI/NO) | E1: Carga inductiva (SI/NO) | F1: Pago con atraso (SI/NO)
A2: E-1 | B2: Mantención autos | C2: 857 | D2: SI | E2: SI | F2: NO
A3: E-2 | B3: Equipamiento eléctrico | C3: 283 | D3: SI | E3: NO | F3: NO
A4: E-3 | B4: Matricería | C4: 870 | D4: SI | E4: SI | F4: NO
A5: E-4 | B5: Matricería | C5: 300 | D5: SI | E5: SI | F5: NO
A6: E-5 | B6: Torno CNC | C6: 508 | D6: NO | E6: SI | F6: NO
A7: E-6 | B7: Torno/Fresadora | C7: 900 | D7: SI | E7: SI | F7: SI
A8: E-7 | B8: Soldadura | C8: 365 | D8: SI | E8: SI | F8: NO
A12: Nota operativa: | B12: Regla: se permite operar hasta 18:00. Si opera después, marcar SI en columna D.
D13: 0.79166667 | G13: =IF(D13="",0,MAX(0,D13-$B6)/MAX(0.000001,(D13-$B5))) -> #VALUE! | H13: =C13*G13 -> #VALUE! | I13: =C13-H13 -> #VALUE!
D14: 0.77083333
D15: 0.77083333
D16: 0.77083333
D17: 0.77083333
D18: 0.79166667
D19: 0.77083333
B24: =C13 -> 0 | C24: =IFERROR(B24/SUM(B24:B30),0) -> 0 | D24: =C24*$G5 -> 0 | E24: =H13 -> #VALUE! | F24: =IFERROR(E24/SUM(E24:E30),0) -> 0 | G24: =F24*$G6 -> 0 | H24: =IF($E13="SI",1,0)/MAX(1,COUNTIF($E13:$E19,"SI")) -> 0 | I24: =H24*$G7 -> 0 | J24: =($G8*0.5/7)+($G8*0.5*C24) -> 0 | K24: =IF($F13="SI",1,0)/MAX(1,COUNTIF($F13:$F19,"SI")) -> 0 | L24: =K24*$G$9 -> 0 | M24: =D24+G24+I24+J24+L24 -> 0
C25: =IFERROR(B25/SUM(B24:B30),0) -> 0 | L25: =K25*$G$9 -> 0
L26: =K26*$G$9 -> 0
L27: =K27*$G$9 -> 0
L28: =K28*$G$9 -> 0
L29: =K29*$G$9 -> 0
L30: =K30*$G$9 -> 0
D31: =SUM(D24:D30) -> 0 | G31: =SUM(G24:G30) -> 0 | I31: =SUM(I24:I30) -> 0 | J31: =SUM(J24:J30) -> 0 | L31: =SUM(L24:L30) -> 0

Sheet Boleta_CGE
A1: Electricidad Consumida $ | B1: Potencia Punta $ | C1: Multa Reactiva $ | D1: Cargos Fijos $ | E1: Intereses/Mora $
A2: 337537 | B2: 261203 | C2: 95798 | D2: 44477 | E2: 35294
A4: Detalle cargos fijos (referencia boleta) | B4: Monto $
A5: Administración del Servicio | B5: 870
A6: Transporte de Electricidad | B6: 33967
A7: Cargo por Servicio Público | B7: 2205
A8: Fondo Estabilización Ley 21.472 | B8: 7435

Sheet Liquidacion
A1: Bodega | B1: kWh | C1: % Energía | D1: $ Energía | E1: % Punta | F1: $ Punta | G1: % Reactiva | H1: $ Reactiva | I1: $ Cargos Fijos | J1: % Interés | K1: $ Interés | L1: TOTAL NETO$ | M1: TOTAL
A2: E-1 | B2: =Inputs_Mes!C2 -> 857 | C2: =IFERROR(B2/SUM(B$2:B$8),0) -> 0.20989469 | D2: =C2*Boleta_CGE!A2 -> 70847.222 | E2: {=IF(Inputs_Mes!D2="SI",1,0)/MAX(1,SUMPRODUCT(--(Inputs_Mes!D$2:D$8="SI")))} -> 0.16666667 | F2: =E2*Boleta_CGE!B2 -> 43533.833 | G2: {=IF(Inputs_Mes!E2="SI",1,0)/MAX(1,SUMPRODUCT(--(Inputs_Mes!E$2:E$8="SI")))} -> 0.16666667 | H2: =G2*Boleta_CGE!C2 -> 15966.333 | I2: =(Boleta_CGE!D2*0.5/7)+(Boleta_CGE!D2*0.5*C2) -> 7844.6715 | J2: {=IF(Inputs_Mes!F2="SI",1,0)/MAX(1,SUMPRODUCT(--(Inputs_Mes!F2:F8="SI")))} -> 0 | K2: =J2*Boleta_CGE!E2 -> 0 | L2: =D2+F2+H2+I2+K2 -> 138192.06 | M2: =L2*1.19 -> 164448.55
A3: E-2 | B3: =Inputs_Mes!C3 -> 283 | C3: =IFERROR(B3/SUM(B$2:B$8),0) -> 0.069311781 | D3: =C3*Boleta_CGE!A2 -> 23395.29 | E3: =IF(Inputs_Mes!D3="SI",1,0)/MAX(1,SUMPRODUCT(--(Inputs_Mes!D$2:D$8="SI"))) -> 0.16666667 | F3: =E3*Boleta_CGE!B2 -> 43533.833 | G3: =IF(Inputs_Mes!E3="SI",1,0)/MAX(1,SUMPRODUCT(--(Inputs_Mes!E$2:E$8="SI"))) -> 0 | H3: =G3*Boleta_CGE!C2 -> 0 | I3: =(Boleta_CGE!D2*0.5/7)+(Boleta_CGE!D2*0.5*C3) -> 4718.3186 | J3: =IF(Inputs_Mes!F3="SI",1,0)/MAX(1,SUMPRODUCT(--(Inputs_Mes!F2:F8="SI"))) -> 0 | K3: =J3*Boleta_CGE!E2 -> 0 | L3: =D3+F3+H3+I3+K3 -> 71647.442 | M3: =L3*1.19 -> 85260.456
A4: E-3 | B4: =Inputs_Mes!C4 -> 870 | C4: =IFERROR(B4/SUM(B$2:B$8),0) -> 0.21307862 | D4: =C4*Boleta_CGE!A2 -> 71921.918 | E4: =IF(Inputs_Mes!D4="SI",1,0)/MAX(1,SUMPRODUCT(--(Inputs_Mes!D$2:D$8="SI"))) -> 0.16666667 | F4: =E4*Boleta_CGE!B2 -> 43533.833 | G4: =IF(Inputs_Mes!E4="SI",1,0)/MAX(1,SUMPRODUCT(--(Inputs_Mes!E$2:E$8="SI"))) -> 0.16666667 | H4: =G4*Boleta_CGE!C2 -> 15966.333 | I4: =(Boleta_CGE!D2*0.5/7)+(Boleta_CGE!D2*0.5*C4) -> 7915.4774 | J4: =IF(Inputs_Mes!F4="SI",1,0)/MAX(1,SUMPRODUCT(--(Inputs_Mes!F2:F8="SI"))) -> 0 | K4: =J4*Boleta_CGE!E2 -> 0 | L4: =D4+F4+H4+I4+K4 -> 139337.56 | M4: =L4*1.19 -> 165811.7
A5: E-4 | B5: =Inputs_Mes!C5 -> 300 | C5: =IFERROR(B5/SUM(B$2:B$8),0) -> 0.073475386 | D5: =C5*Boleta_CGE!A2 -> 24800.661 | E5: =IF(Inputs_Mes!D5="SI",1,0)/MAX(1,SUMPRODUCT(--(Inputs_Mes!D$2:D$8="SI"))) -> 0.16666667 | F5: =E5*Boleta_CGE!B2 -> 43533.833 | G5: =IF(Inputs_Mes!E5="SI",1,0)/MAX(1,SUMPRODUCT(--(Inputs_Mes!E$2:E$8="SI"))) -> 0.16666667 | H5: =G5*Boleta_CGE!C2 -> 15966.333 | I5: =(Boleta_CGE!D2*0.5/7)+(Boleta_CGE!D2*0.5*C5) -> 4810.9109 | J5: =IF(Inputs_Mes!F5="SI",1,0)/MAX(1,SUMPRODUCT(--(Inputs_Mes!F2:F8="SI"))) -> 0 | K5: =J5*Boleta_CGE!E2 -> 0 | L5: =D5+F5+H5+I5+K5 -> 89111.739 | M5: =L5*1.19 -> 106042.97
A6: E-5 | B6: =Inputs_Mes!C6 -> 508 | C6: =IFERROR(B6/SUM(B$2:B$8),0) -> 0.12441832 | D6: =C6*Boleta_CGE!A2 -> 41995.786 | E6: =IF(Inputs_Mes!D6="SI",1,0)/MAX(1,SUMPRODUCT(--(Inputs_Mes!D$2:D$8="SI"))) -> 0 | F6: =E6*Boleta_CGE!B2 -> 0 | G6: =IF(Inputs_Mes!E6="SI",1,0)/MAX(1,SUMPRODUCT(--(Inputs_Mes!E$2:E$8="SI"))) -> 0.16666667 | H6: =G6*Boleta_CGE!C2 -> 15966.333 | I6: =(Boleta_CGE!D2*0.5/7)+(Boleta_CGE!D2*0.5*C6) -> 5943.8054 | J6: =IF(Inputs_Mes!F6="SI",1,0)/MAX(1,SUMPRODUCT(--(Inputs_Mes!F2:F8="SI"))) -> 0 | K6: =J6*Boleta_CGE!E2 -> 0 | L6: =D6+F6+H6+I6+K6 -> 63905.925 | M6: =L6*1.19 -> 76048.051
A7: E-6 | B7: =Inputs_Mes!C7 -> 900 | C7: =IFERROR(B7/SUM(B$2:B$8),0) -> 0.22042616 | D7: =C7*Boleta_CGE!A2 -> 74401.984 | E7: =IF(Inputs_Mes!D7="SI",1,0)/MAX(1,SUMPRODUCT(--(Inputs_Mes!D$2:D$8="SI"))) -> 0.16666667 | F7: =E7*Boleta_CGE!B2 -> 43533.833 | G7: =IF(Inputs_Mes!E7="SI",1,0)/MAX(1,SUMPRODUCT(--(Inputs_Mes!E$2:E$8="SI"))) -> 0.16666667 | H7: =G7*Boleta_CGE!C2 -> 15966.333 | I7: =(Boleta_CGE!D2*0.5/7)+(Boleta_CGE!D2*0.5*C7) -> 8078.8757 | J7: =IF(Inputs_Mes!F7="SI",1,0)/MAX(1,SUMPRODUCT(--(Inputs_Mes!F2:F8="SI"))) -> 1 | K7: =J7*Boleta_CGE!E2 -> 35294 | L7: =D7+F7+H7+I7+K7 -> 177275.03 | M7: =L7*1.19 -> 210957.28
A8: E-7 | B8: =Inputs_Mes!C8 -> 365 | C8: =IFERROR(B8/SUM(B$2:B$8),0) -> 0.089395053 | D8: =C8*Boleta_CGE!A2 -> 30174.138 | E8: =IF(Inputs_Mes!D8="SI",1,0)/MAX(1,SUMPRODUCT(--(Inputs_Mes!D$2:D$8="SI"))) -> 0.16666667 | F8: =E8*Boleta_CGE!B2 -> 43533.833 | G8: =IF(Inputs_Mes!E8="SI",1,0)/MAX(1,SUMPRODUCT(--(Inputs_Mes!E$2:E$8="SI"))) -> 0.16666667 | H8: =G8*Boleta_CGE!C2 -> 15966.333 | I8: =(Boleta_CGE!D2*0.5/7)+(Boleta_CGE!D2*0.5*C8) -> 5164.9404 | J8: =IF(Inputs_Mes!F8="SI",1,0)/MAX(1,SUMPRODUCT(--(Inputs_Mes!F2:F8="SI"))) -> 0 | K8: =J8*Boleta_CGE!E2 -> 0 | L8: =D8+F8+H8+I8+K8 -> 94839.245 | M8: =L8*1.19 -> 112858.7
A10: TOTAL | B10: =SUM(B2:B8) -> 4083 | D10: =SUM(D2:D8) -> 337537 | F10: =SUM(F2:F8) -> 261203 | H10: =SUM(H2:H8) -> 95798 | I10: =SUM(I2:I8) -> 44477 | K10: =SUM(K2:K8) -> 35294 | L10: =SUM(L2:L8) -> 774309 | M10: =L10*1.19 -> 921427.71
A12: Nota: Intereses/Mora | B12: Boleta_CGE!E2 se asigna manualmente al responsable del atraso (no se prorratea).
